biznes/__init__.py
biznes/__main__.py
biznes/shell.py
biznes/tui.py
biznes/core/__init__.py
biznes/core/models.py
biznes/legal/__init__.py
biznes/scenarios/__init__.py
biznes/scenarios/engine.py
biznes/utils/__init__.py
biznes/utils/guidance.py
biznes/utils/shell_context.py
biznes-1.0.9.dist-info/licenses/LICENSE
biznes-1.0.9.dist-info/METADATA
biznes-1.0.9.dist-info/WHEEL
biznes-1.0.9.dist-info/entry_points.txt
biznes-1.0.9.dist-info/top_level.txt
biznes-1.0.9.dist-info/RECORD
