Metadata-Version: 2.4
Name: biznes
Version: 1.0.9
Summary: Interaktywny symulator startupu - edukacyjna gra o zakładaniu firmy w Polsce
Author-email: Softreck <info@softreck.dev>
License: MIT
Project-URL: Homepage, https://github.com/softreck/biznes
Keywords: startup,education,game,simulation,business,poland
Classifier: Development Status :: 4 - Beta
Classifier: Environment :: Console
Classifier: Intended Audience :: Education
Classifier: License :: OSI Approved :: MIT License
Classifier: Natural Language :: Polish
Classifier: Programming Language :: Python :: 3
Classifier: Topic :: Games/Entertainment :: Simulation
Requires-Python: >=3.8
License-File: LICENSE
Requires-Dist: pyyaml>=6.0
Provides-Extra: dev
Requires-Dist: pytest>=7.0; extra == "dev"
Requires-Dist: black; extra == "dev"
Requires-Dist: mypy; extra == "dev"
Provides-Extra: tui
Requires-Dist: textual>=0.40.0; extra == "tui"
Dynamic: license-file
